Capeify/main.py
Capeify/ani_file/Iconolatry.py
Capeify/ani_file/__init__.py
Capeify/ani_file/ani_file.py
Capeify/scripts/.gitkeep
Capeify/scripts/__init__.py
Capeify/scripts/create_xml.py
Capeify/scripts/read_inf.py
Capeify/scripts/ani/.gitkeep
Capeify/scripts/ani/__init__.py
Capeify/scripts/ani/convert2png.py
Capeify/scripts/ani/get_frame_duration.py
Capeify/scripts/ani/get_hotspot.py
Capeify/scripts/ani/get_size.py
Capeify/scripts/cur/.gitkeep
Capeify/scripts/cur/__init__.py
Capeify/scripts/cur/convert2png.py
Capeify/scripts/cur/get_hotspot.py
Capeify/scripts/cur/get_size.py
Capeify/templates/cape_template.cape
Capeify/templates/cursor_template.cape
capeify-1.1.3.dist-info/METADATA
capeify-1.1.3.dist-info/WHEEL
capeify-1.1.3.dist-info/entry_points.txt
capeify-1.1.3.dist-info/top_level.txt
capeify-1.1.3.dist-info/RECORD
