Metadata-Version: 2.4
Name: capeify
Version: 1.1.3
Summary: Win cursor package to .cape file converter
Author: mmemoo
Requires-Python: <=3.12,>=3.10
Requires-Dist: Wand
Requires-Dist: Pillow
Requires-Dist: lxml
